pymbta3/__init__.py
pymbta3/pymbta3.py
pymbta3-0.0.5.dev0.dist-info/LICENSE
pymbta3-0.0.5.dev0.dist-info/METADATA
pymbta3-0.0.5.dev0.dist-info/WHEEL
pymbta3-0.0.5.dev0.dist-info/top_level.txt
pymbta3-0.0.5.dev0.dist-info/RECORD
