Metadata-Version: 2.1
Name: pymbta3
Version: 0.0.5.dev0
Home-page: https://github.com/altonplace/pymbta3
Author: Mike Anderson
License: MIT
Keywords: mbta api
Classifier: License :: OSI Approved :: MIT License
Classifier: Development Status :: 3 - Alpha
Classifier: Programming Language :: Python :: 3
Classifier: Programming Language :: Python :: 3.7
License-File: LICENSE
Requires-Dist: requests
